motionscene_merger/__init__.py
motionscene_merger/scenemerge.py
motionscene_merger-2.4.1.dist-info/LICENSE
motionscene_merger-2.4.1.dist-info/METADATA
motionscene_merger-2.4.1.dist-info/WHEEL
motionscene_merger-2.4.1.dist-info/entry_points.txt
motionscene_merger-2.4.1.dist-info/top_level.txt
motionscene_merger-2.4.1.dist-info/RECORD
