Metadata-Version: 2.1
Name: motionscene-merger
Version: 2.4.1
Summary: File injection tool for Android developers using MotionLayout. Use scenemerge to reuse ConstraintSet/KeyFrameSet/etc definitions in multiple MotionScenes via a templating system.
Home-page: https://github.com/beatonma/motionscene-merger
Author: Michael Beaton
Author-email: michael@beatonma.org
License: GNU General Public License v3.0
Platform: UNKNOWN
Classifier: Programming Language :: Python :: 3
Classifier: Intended Audience :: Developers
Classifier: License :: OSI Approved :: GNU General Public License v3 (GPLv3)
Requires-Python: >=3.6
